llmprompt_nexus/__init__.py
llmprompt_nexus/clients/__init__.py
llmprompt_nexus/clients/base.py
llmprompt_nexus/clients/client_factory.py
llmprompt_nexus/clients/openai_client.py
llmprompt_nexus/clients/perplexity_client.py
llmprompt_nexus/config/models/openai.yaml
llmprompt_nexus/config/models/perplexity.yaml
llmprompt_nexus/config/templates/classification.yaml
llmprompt_nexus/config/templates/default.yaml
llmprompt_nexus/config/templates/intent.yaml
llmprompt_nexus/config/templates/qa.yaml
llmprompt_nexus/config/templates/summarization.yaml
llmprompt_nexus/config/templates/translation.yaml
llmprompt_nexus/models/__init__.py
llmprompt_nexus/models/config.py
llmprompt_nexus/models/model_config.py
llmprompt_nexus/models/registry.py
llmprompt_nexus/nexus_manager.py
llmprompt_nexus/processors/base.py
llmprompt_nexus/processors/factory.py
llmprompt_nexus/processors/openai.py
llmprompt_nexus/processors/perplexity.py
llmprompt_nexus/rate_limiting/__init__.py
llmprompt_nexus/rate_limiting/limiter.py
llmprompt_nexus/templates/__init__.py
llmprompt_nexus/templates/base.py
llmprompt_nexus/templates/manager.py
llmprompt_nexus/utils/__init__.py
llmprompt_nexus/utils/logger.py
llmprompt_nexus/utils/progress.py
llmprompt_nexus-0.2.1.dist-info/LICENSE
llmprompt_nexus-0.2.1.dist-info/METADATA
llmprompt_nexus-0.2.1.dist-info/WHEEL
llmprompt_nexus-0.2.1.dist-info/RECORD
