Metadata-Version: 2.3
Name: llmprompt-nexus
Version: 0.2.1
Summary: A unified framework for interacting with various LLM providers through a consistent interface with batch processing, templating, and rate limiting.
License: CC-BY-NC-4.0
Author: Ernesto Estevanell
Author-email: ernestoestevanellv@gmail.com
Requires-Python: >=3.9
Classifier: License :: Other/Proprietary License
Classifier: Programming Language :: Python :: 3
Classifier: Programming Language :: Python :: 3.9
Classifier: Programming Language :: Python :: 3.10
Classifier: Programming Language :: Python :: 3.11
Classifier: Programming Language :: Python :: 3.12
Classifier: Programming Language :: Python :: 3.13
Requires-Dist: aiohttp (==3.9.3)
Requires-Dist: httpx (>=0.28.1,<0.29.0)
Requires-Dist: numpy (==1.26.4)
Requires-Dist: pandas (==1.5.3)
Requires-Dist: python-dotenv (==1.0.0)
Requires-Dist: pyyaml (==6.0.1)
Requires-Dist: tqdm (==4.66.2)
